{
  "repo": "devpath-frontend",
  "updatedAt": "2026-06-13T01:35:50.689Z",
  "tracks": [
    {
      "name": "frontend",
      "owner": "Frontend/Mobile",
      "weeks": [
        {
          "week": "W4",
          "period": "07-06~07-10",
          "steps": [
            {
              "name": "랜딩 페이지",
              "status": "Not Started",
              "phases": [
                {
                  "name": "랜딩 페이지",
                  "total": 1,
                  "done": 0,
                  "items": [
                    {
                      "text": "랜딩 페이지(히어로 데모 영상)",
                      "done": false
                    }
                  ]
                }
              ],
              "totalChecks": 1,
              "doneChecks": 0
            }
          ],
          "totalChecks": 1,
          "doneChecks": 0
        },
        {
          "week": "W5",
          "period": "07-13~07-17",
          "steps": [
            {
              "name": "진단 UI",
              "status": "Not Started",
              "phases": [
                {
                  "name": "진단 UI",
                  "total": 1,
                  "done": 0,
                  "items": [
                    {
                      "text": "객관식 + 코드 읽기 진단 UI",
                      "done": false
                    }
                  ]
                }
              ],
              "totalChecks": 1,
              "doneChecks": 0
            }
          ],
          "totalChecks": 1,
          "doneChecks": 0
        },
        {
          "week": "W8",
          "period": "08-03~08-07",
          "steps": [
            {
              "name": "1st Aha 화면",
              "status": "Not Started",
              "phases": [
                {
                  "name": "1st Aha 화면",
                  "total": 3,
                  "done": 0,
                  "items": [
                    {
                      "text": "학습 경로 시각화 화면",
                      "done": false
                    },
                    {
                      "text": "단일 CTA 검증",
                      "done": false
                    },
                    {
                      "text": "Q&A UI",
                      "done": false
                    }
                  ]
                }
              ],
              "totalChecks": 3,
              "doneChecks": 0
            }
          ],
          "totalChecks": 3,
          "doneChecks": 0
        },
        {
          "week": "W9",
          "period": "08-10~08-14",
          "steps": [
            {
              "name": "콘텐츠 뷰어",
              "status": "Not Started",
              "phases": [
                {
                  "name": "콘텐츠 뷰어",
                  "total": 2,
                  "done": 0,
                  "items": [
                    {
                      "text": "Markdown + Syntax Highlighting",
                      "done": false
                    },
                    {
                      "text": "코드 블록 인라인 실행 팝오버",
                      "done": false
                    }
                  ]
                }
              ],
              "totalChecks": 2,
              "doneChecks": 0
            }
          ],
          "totalChecks": 2,
          "doneChecks": 0
        },
        {
          "week": "W11",
          "period": "08-24~08-28",
          "steps": [
            {
              "name": "Monaco 에디터",
              "status": "Not Started",
              "phases": [
                {
                  "name": "Monaco 에디터",
                  "total": 1,
                  "done": 0,
                  "items": [
                    {
                      "text": "Web Monaco 에디터 통합",
                      "done": false
                    }
                  ]
                }
              ],
              "totalChecks": 1,
              "doneChecks": 0
            }
          ],
          "totalChecks": 1,
          "doneChecks": 0
        },
        {
          "week": "W13",
          "period": "09-07~09-11",
          "steps": [
            {
              "name": "모바일 앱 기본",
              "status": "Not Started",
              "phases": [
                {
                  "name": "모바일 앱 기본",
                  "total": 3,
                  "done": 0,
                  "items": [
                    {
                      "text": "Flutter 앱 스캐폴드(OAuth2 + JWT)",
                      "done": false
                    },
                    {
                      "text": "홈 대시보드(스트릭·진척률·다음 과제)",
                      "done": false
                    },
                    {
                      "text": "딥링크 + FCM 푸시 기반",
                      "done": false
                    }
                  ]
                }
              ],
              "totalChecks": 3,
              "doneChecks": 0
            }
          ],
          "totalChecks": 3,
          "doneChecks": 0
        },
        {
          "week": "W14",
          "period": "09-14~09-18",
          "steps": [
            {
              "name": "모바일 학습 뷰어",
              "status": "Not Started",
              "phases": [
                {
                  "name": "모바일 학습 뷰어",
                  "total": 3,
                  "done": 0,
                  "items": [
                    {
                      "text": "콘텐츠 뷰어(Markdown + 코드)",
                      "done": false
                    },
                    {
                      "text": "진척도 동기화",
                      "done": false
                    },
                    {
                      "text": "오프라인 읽기 캐시(drift)",
                      "done": false
                    }
                  ]
                }
              ],
              "totalChecks": 3,
              "doneChecks": 0
            }
          ],
          "totalChecks": 3,
          "doneChecks": 0
        },
        {
          "week": "W16",
          "period": "09-28~10-02",
          "steps": [
            {
              "name": "프로필 + UX",
              "status": "Not Started",
              "phases": [
                {
                  "name": "프로필 + UX",
                  "total": 3,
                  "done": 0,
                  "items": [
                    {
                      "text": "사용자 프로필 화면(평판·태그평판·배지 슬롯)",
                      "done": false
                    },
                    {
                      "text": "모바일 퀵 캡처",
                      "done": false
                    },
                    {
                      "text": "UX 회귀 + 성능 튜닝",
                      "done": false
                    }
                  ]
                }
              ],
              "totalChecks": 3,
              "doneChecks": 0
            }
          ],
          "totalChecks": 3,
          "doneChecks": 0
        },
        {
          "week": "W19",
          "period": "10-19~10-23",
          "steps": [
            {
              "name": "대시보드 UI",
              "status": "Not Started",
              "phases": [
                {
                  "name": "대시보드 UI",
                  "total": 1,
                  "done": 0,
                  "items": [
                    {
                      "text": "진척·리텐션 대시보드 UI(홈)",
                      "done": false
                    }
                  ]
                }
              ],
              "totalChecks": 1,
              "doneChecks": 0
            }
          ],
          "totalChecks": 1,
          "doneChecks": 0
        }
      ]
    }
  ],
  "prd": [],
  "history": [],
  "changelog": []
}
